{"TestCases":[{"AutomationId":"8e2e95b0-2c3d-4712-a24c-54458ec5cda1","TestCaseName":"Assess policy term impact on premium calculation.cs","RpaPackageEntryPoints":[],"RpaWorkflows":[]},{"AutomationId":"1b04f52d-1078-44eb-93ae-a3e4f645bbdc","TestCaseName":"Check coverage amount impact on premium calculation.cs","RpaPackageEntryPoints":[],"RpaWorkflows":[]},{"AutomationId":"c0ace06c-98f2-4d7e-b7cb-803616d626cc","TestCaseName":"Check the password length requirement.cs","RpaPackageEntryPoints":[],"RpaWorkflows":[]},{"AutomationId":"0de2ba2f-19f7-4455-bdcb-ba5bc88384a3","TestCaseName":"Examine health conditions impact on premium calculation.cs","RpaPackageEntryPoints":[],"RpaWorkflows":[]},{"AutomationId":"612a59f5-b88a-42d8-ab9a-626a9ac821b8","TestCaseName":"Test smoking status impact on premium calculation.cs","RpaPackageEntryPoints":[],"RpaWorkflows":[]},{"AutomationId":"16309db6-c9be-46be-b619-785d0b107e01","TestCaseName":"Validate gender consideration in premium calculation.cs","RpaPackageEntryPoints":[],"RpaWorkflows":[]},{"AutomationId":"7f9fb605-659c-4390-8a70-7d83de19d934","TestCaseName":"Verify age impact on premium calculation.cs","RpaPackageEntryPoints":[],"RpaWorkflows":[]},{"AutomationId":"03949461-526b-4bc8-858e-3a0d7951490e","TestCaseName":"Verify the presence of registration page.cs","RpaPackageEntryPoints":[],"RpaWorkflows":[]},{"AutomationId":"4d357b8e-a6e8-4793-a60e-33c813d2cc6e","TestCaseName":"Test input of transfer amount.cs","RpaPackageEntryPoints":[],"RpaWorkflows":[]},{"AutomationId":"f493d57e-7846-41b7-88d4-1026a229ae94","TestCaseName":"Test successful registration.cs","RpaPackageEntryPoints":[],"RpaWorkflows":[]},{"AutomationId":"3af52db1-c851-4e88-94e5-0f165dd752d3","TestCaseName":"Test transfer execution.cs","RpaPackageEntryPoints":[],"RpaWorkflows":[]},{"AutomationId":"d0701ff0-d437-4a0f-81d9-b76be7d2ab8e","TestCaseName":"Validate account selection for fund transfer.cs","RpaPackageEntryPoints":[],"RpaWorkflows":[]},{"AutomationId":"6c73ad41-a18f-480d-9605-8839e0c04a74","TestCaseName":"Validate conditional transfer limits.cs","RpaPackageEntryPoints":[],"RpaWorkflows":[]},{"AutomationId":"0dcc3d4c-5d63-45c3-8e15-514d2c5dec3d","TestCaseName":"Validate error handling for fund transfer.cs","RpaPackageEntryPoints":[],"RpaWorkflows":[]},{"AutomationId":"805b09d0-9fc3-4900-8791-5890dd7b3887","TestCaseName":"Validate the email uniqueness.cs","RpaPackageEntryPoints":[],"RpaWorkflows":[]},{"AutomationId":"42ea447a-5cb8-4270-9329-02151924dfda","TestCaseName":"Verify loan application for applicants below 18 years of age.cs","RpaPackageEntryPoints":[],"RpaWorkflows":[]},{"AutomationId":"dba8e08a-7f18-441c-a881-1b9a3c2c2c1c","TestCaseName":"Verify loan application with valid data and loan amount below 100.000.cs","RpaPackageEntryPoints":[],"RpaWorkflows":[]},{"AutomationId":"78da252a-eff3-48ff-82b4-d533ae44b5f6","TestCaseName":"Verify loan application with valid data and loan amount over 100.000.cs","RpaPackageEntryPoints":[],"RpaWorkflows":[]},{"AutomationId":"26da127d-f82d-4cf5-8bdd-fb497d9de241","TestCaseName":"Verify loan application without filling all mandatory fields.cs","RpaPackageEntryPoints":[],"RpaWorkflows":[]},{"AutomationId":"62c19757-46ed-4282-9074-fe0b66fbf55c","TestCaseName":"Verify the password complexity.cs","RpaPackageEntryPoints":[],"RpaWorkflows":[]},{"AutomationId":"3968b3f2-dd11-46ee-9adb-3700757f90a1","TestCaseName":"Validate the email format.cs","RpaPackageEntryPoints":[],"RpaWorkflows":[]},{"AutomationId":"6a077625-c166-4c22-8336-e85595e800cc","TestCaseName":"Verify transaction history update.cs","RpaPackageEntryPoints":[],"RpaWorkflows":[]},{"AutomationId":"f39f8eb6-2a97-4516-aae9-327ee79b78a6","TestCaseName":"Verify transfer confirmation dialog.cs","RpaPackageEntryPoints":[],"RpaWorkflows":[]},{"AutomationId":"b5caadec-8df8-4cd8-a942-3e7a158bb174","TestCaseName":"Verify user authentication before fund transfer.cs","RpaPackageEntryPoints":[],"RpaWorkflows":[]}],"Workflows":[],"PackageName":"TSDO","PackageVersion":"1.0.164732410","RpaPackageName":"TSDO","RpaPackageVersion":"1.0.164731645","ProjectId":"e3046da8-a0d7-4cb2-8b14-f87de36b6210"}